nbprocess/__init__.py
nbprocess/_modidx.py
nbprocess/clean.py
nbprocess/cli.py
nbprocess/doclinks.py
nbprocess/export.py
nbprocess/extract_attachments.py
nbprocess/imports.py
nbprocess/maker.py
nbprocess/merge.py
nbprocess/migrate.py
nbprocess/mkdocs.py
nbprocess/process.py
nbprocess/processors.py
nbprocess/read.py
nbprocess/shortcuts.py
nbprocess/showdoc.py
nbprocess/sync.py
nbprocess/test.py
nbprocess/tutorial.py
nbprocess-0.0.7.dist-info/LICENSE
nbprocess-0.0.7.dist-info/METADATA
nbprocess-0.0.7.dist-info/WHEEL
nbprocess-0.0.7.dist-info/entry_points.txt
nbprocess-0.0.7.dist-info/top_level.txt
nbprocess-0.0.7.dist-info/RECORD
