Metadata-Version: 2.1
Name: nbprocess
Version: 0.0.7
Summary: Process and export Jupyter Notebooks fast (Jupyter not required)
Home-page: https://github.com/fastai/nbprocess
Author: Jeremy Howard
Author-email: j@fast.ai
License: Apache Software License 2.0
Keywords: nbdev fastai jupyter notebook export
Platform: UNKNOWN
Classifier: Development Status :: 3 - Alpha
Classifier: Intended Audience :: Developers
Classifier: Natural Language :: English
Classifier: Programming Language :: Python :: 3.7
Classifier: Programming Language :: Python :: 3.8
Classifier: Programming Language :: Python :: 3.9
Classifier: Programming Language :: Python :: 3.10
Classifier: License :: OSI Approved :: Apache Software License
Requires-Python: >=3.7
License-File: LICENSE
Requires-Dist: fastcore (>=1.5.5)
Requires-Dist: execnb
Requires-Dist: asttokens ; python_version=="3.7"
Provides-Extra: dev
Requires-Dist: nbdev-numpy ; extra == 'dev'
Requires-Dist: nbdev-stdlib ; extra == 'dev'
Requires-Dist: pandas ; extra == 'dev'
Requires-Dist: matplotlib ; extra == 'dev'
Requires-Dist: ipython ; extra == 'dev'
Requires-Dist: black ; extra == 'dev'
Requires-Dist: ghapi ; extra == 'dev'
